django_outlook_email/__init__.py
django_outlook_email/django_outlook_email_backend.py
django_outlook_email/exceptions/__init__.py
django_outlook_email/exceptions/microsoft_graph_exceptions.py
django_outlook_email/senders/__init__.py
django_outlook_email/senders/base_sender.py
django_outlook_email/senders/content_types.py
django_outlook_email/senders/json_sender.py
django_outlook_email/senders/mime_sender.py
django_outlook_email/senders/attachments/__init__.py
django_outlook_email/senders/attachments/attachments_using_upload_session.py
django_outlook_email/senders/encoders/__init__.py
django_outlook_email/senders/encoders/lazy_encoders.py
django_outlook_email/senders/microsoft_requests/__init__.py
django_outlook_email/senders/microsoft_requests/microsoft_requests.py
django_outlook_email_backend-1.1.24.dist-info/licenses/LICENSE
django_outlook_email_backend-1.1.24.dist-info/METADATA
django_outlook_email_backend-1.1.24.dist-info/WHEEL
django_outlook_email_backend-1.1.24.dist-info/top_level.txt
django_outlook_email_backend-1.1.24.dist-info/zip-safe
django_outlook_email_backend-1.1.24.dist-info/RECORD
