Metadata-Version: 2.4
Name: django_outlook_email-backend
Version: 1.1.24
Summary: Ouauth2 outlook email backend for Django
Home-page: https://github.com/enley-es/django-outlook-email-backend
Author: Marc Claramunt
Author-email: mclaramunt@enley.com
License: MIT
Classifier: Environment :: Web Environment
Classifier: Framework :: Django
Classifier: Intended Audience :: Developers
Classifier: License :: OSI Approved :: MIT License
Classifier: Operating System :: OS Independent
Classifier: Programming Language :: Python
Classifier: Topic :: Software Development :: Libraries :: Python Modules
License-File: LICENSE
Requires-Dist: requests~=2.25
Requires-Dist: msal==1.*
Dynamic: author
Dynamic: author-email
Dynamic: classifier
Dynamic: description
Dynamic: description-content-type
Dynamic: home-page
Dynamic: license
Dynamic: license-file
Dynamic: requires-dist
Dynamic: summary
